nonebot_plugin_steam_game_status/__init__.py
nonebot_plugin_steam_game_status/api.py
nonebot_plugin_steam_game_status/config.py
nonebot_plugin_steam_game_status/model.py
nonebot_plugin_steam_game_status/source.py
nonebot_plugin_steam_game_status/utils.py
nonebot_plugin_steam_game_status-0.2.6.dist-info/WHEEL
nonebot_plugin_steam_game_status-0.2.6.dist-info/METADATA
nonebot_plugin_steam_game_status-0.2.6.dist-info/licenses/LICENSE
nonebot_plugin_steam_game_status-0.2.6.dist-info/RECORD
