Metadata-Version: 2.1
Name: nonebot-plugin-steam-game-status
Version: 0.2.6
Summary: 播报群友 Steam 游戏状态
License: GPL3
Author-email: nek0us <nekouss@mail.com>
Requires-Python: >=3.10
Requires-Dist: beautifulsoup4>=4.13.5
Requires-Dist: nonebot-adapter-onebot>=2.4.2
Requires-Dist: nonebot-plugin-alconna>=0.57.0
Requires-Dist: nonebot-plugin-apscheduler>=0.2.0
Requires-Dist: nonebot2>=2.0.0
Requires-Dist: nonebot_plugin_htmlrender>=0.3.1
Requires-Dist: nonebot_plugin_localstore>=0.7.1
Project-URL: Homepage, https://github.com/nek0us/nonebot_plugin_steam_game_status
Project-URL: Repository, https://github.com/nek0us/nonebot_plugin_steam_game_status
